scene_synthesizer/__init__.py
scene_synthesizer/assets.py
scene_synthesizer/constants.py
scene_synthesizer/datasets.py
scene_synthesizer/datasets_cmdline.py
scene_synthesizer/default_config.yaml
scene_synthesizer/procedural_assets.py
scene_synthesizer/procedural_scenes.py
scene_synthesizer/scene.py
scene_synthesizer/trimesh_utils.py
scene_synthesizer/usd_import.py
scene_synthesizer/utils.py
scene_synthesizer/exchange/__init__.py
scene_synthesizer/exchange/export.py
scene_synthesizer/exchange/urdf.py
scene_synthesizer/exchange/usd.py
scene_synthesizer/exchange/usd_export.py
scene_synthesizer-1.15.0.dist-info/LICENSE
scene_synthesizer-1.15.0.dist-info/METADATA
scene_synthesizer-1.15.0.dist-info/WHEEL
scene_synthesizer-1.15.0.dist-info/entry_points.txt
scene_synthesizer-1.15.0.dist-info/top_level.txt
scene_synthesizer-1.15.0.dist-info/RECORD
