Metadata-Version: 2.1
Name: scene_synthesizer
Version: 1.15.0
Summary: Quickly generate a random articulated scene for robotics research and applications
Home-page: https://github.com/NVlabs/scene_synthesizer
Author: Clemens Eppner et al.
Author-email: ceppner@nvidia.com
License: Apache-2.0
Platform: any
Classifier: License :: OSI Approved :: Apache Software License
Classifier: Operating System :: OS Independent
Classifier: Intended Audience :: Developers
Classifier: Natural Language :: English
Classifier: Programming Language :: Python :: 3
Classifier: Topic :: Scientific/Engineering :: Artificial Intelligence
Classifier: Framework :: Robot Framework :: Library
License-File: LICENSE
Requires-Dist: matplotlib
Requires-Dist: numpy
Requires-Dist: networkx>=2.5
Requires-Dist: python-fcl>=0.7.0.8
Requires-Dist: pyyaml
Requires-Dist: rtree
Requires-Dist: setuptools-scm>=6.2
Requires-Dist: shapely>=2.0.0
Requires-Dist: triangle
Requires-Dist: trimesh[easy]
Requires-Dist: yourdfpy>=0.0.53
Requires-Dist: config-path
Provides-Extra: all
Requires-Dist: pyglet<2; extra == "all"
Requires-Dist: usd-core; extra == "all"
Requires-Dist: dm-control; extra == "all"
Requires-Dist: trimesh[easy,recommend]; extra == "all"
Provides-Extra: ci
Requires-Dist: anybadge; extra == "ci"
Requires-Dist: black==22.10.0; extra == "ci"
Requires-Dist: build; extra == "ci"
Requires-Dist: coverage; extra == "ci"
Requires-Dist: flake8; extra == "ci"
Requires-Dist: flake8-docstrings; extra == "ci"
Requires-Dist: flake8-isort; extra == "ci"
Requires-Dist: pytest; extra == "ci"
Requires-Dist: pytest-cov; extra == "ci"
Requires-Dist: pytest-xdist; extra == "ci"
Requires-Dist: pytest-timeout; extra == "ci"
Requires-Dist: sphinx; extra == "ci"
Requires-Dist: sphinx-rtd-theme; extra == "ci"
Requires-Dist: sphinxcontrib-bibtex; extra == "ci"
Requires-Dist: twine; extra == "ci"
Provides-Extra: dev
Requires-Dist: ipdb; extra == "dev"
Requires-Dist: ipython; extra == "dev"
Requires-Dist: jinja2==3.0; extra == "dev"
Provides-Extra: recommend
Requires-Dist: usd-core; extra == "recommend"
Requires-Dist: dm-control; extra == "recommend"
